[ {
  "relationType" : "ORG-AFF",
  "extent" : "some friends that owned oil companies (oil was used in lamps)",
  "sentence_length" : 42,
  "mentionArg2" : {
    "extent" : "oil companies",
    "argMentionid" : "MARKBACKER_20041103.1300-E4-7",
    "start" : 32,
    "end" : 33
  },
  "relationID" : "MARKBACKER_20041103.1300-R1",
  "mentionArg1" : {
    "extent" : "that",
    "argMentionid" : "MARKBACKER_20041103.1300-E3-6",
    "start" : 30,
    "end" : 30
  },
  "id" : "MARKBACKER_20041103.1300-R1-1",
  "relationSubType" : "Ownership",
  "Sentence" : "I kept reading the website of propoganda and found that the first person to come up with the idea was Benjamin Franklin who did it on behalf of some friends that owned oil companies ( oil was used in lamps ) .",
  "sentence_index" : 10,
  "Tokens" : [ "I", "kept", "reading", "the", "website", "of", "propoganda", "and", "found", "that", "the", "first", "person", "to", "come", "up", "with", "the", "idea", "was", "Benjamin", "Franklin", "who", "did", "it", "on", "behalf", "of", "some", "friends", "that", "owned", "oil", "companies", "(", "oil", "was", "used", "in", "lamps", ")", "." ]
}, {
  "relationType" : "PER-SOC",
  "extent" : "I kept reading the website of propoganda and found that the first person to come up with the idea was Benjamin Franklin who did it on behalf of some friends that owned oil companies (oil was used in lamps)",
  "sentence_length" : 42,
  "mentionArg2" : {
    "extent" : "some friends that owned oil companies (oil was used in lamps)",
    "argMentionid" : "MARKBACKER_20041103.1300-E3-5",
    "start" : 28,
    "end" : 40
  },
  "relationID" : "MARKBACKER_20041103.1300-R2",
  "mentionArg1" : {
    "extent" : "who",
    "argMentionid" : "MARKBACKER_20041103.1300-E1-4",
    "start" : 22,
    "end" : 22
  },
  "id" : "MARKBACKER_20041103.1300-R2-1",
  "relationSubType" : "Lasting-Personal",
  "Sentence" : "I kept reading the website of propoganda and found that the first person to come up with the idea was Benjamin Franklin who did it on behalf of some friends that owned oil companies ( oil was used in lamps ) .",
  "sentence_index" : 10,
  "Tokens" : [ "I", "kept", "reading", "the", "website", "of", "propoganda", "and", "found", "that", "the", "first", "person", "to", "come", "up", "with", "the", "idea", "was", "Benjamin", "Franklin", "who", "did", "it", "on", "behalf", "of", "some", "friends", "that", "owned", "oil", "companies", "(", "oil", "was", "used", "in", "lamps", ")", "." ]
}, {
  "relationType" : "PART-WHOLE",
  "extent" : "Indiana's eastern half",
  "sentence_length" : 39,
  "mentionArg2" : {
    "extent" : "Indiana",
    "argMentionid" : "MARKBACKER_20041103.1300-E15-24",
    "start" : 30,
    "end" : 30
  },
  "relationID" : "MARKBACKER_20041103.1300-R3",
  "mentionArg1" : {
    "extent" : "Indiana's eastern half",
    "argMentionid" : "MARKBACKER_20041103.1300-E14-23",
    "start" : 30,
    "end" : 33
  },
  "id" : "MARKBACKER_20041103.1300-R3-1",
  "relationSubType" : "Geographical",
  "Sentence" : "There 's a LOT more to this since then , and you can read a lot more it if you want to , but this is what I know : Indiana 's eastern half does n't use it .",
  "sentence_index" : 16,
  "Tokens" : [ "There", "'s", "a", "LOT", "more", "to", "this", "since", "then", ",", "and", "you", "can", "read", "a", "lot", "more", "it", "if", "you", "want", "to", ",", "but", "this", "is", "what", "I", "know", ":", "Indiana", "'s", "eastern", "half", "does", "n't", "use", "it", "." ]
}, {
  "relationType" : "PHYS",
  "extent" : "Arizona doesn't use it because one tribe of Indians stretches into three states",
  "sentence_length" : 15,
  "mentionArg2" : {
    "extent" : "three states",
    "argMentionid" : "MARKBACKER_20041103.1300-E19-28",
    "start" : 12,
    "end" : 13
  },
  "relationID" : "MARKBACKER_20041103.1300-R4",
  "mentionArg1" : {
    "extent" : "one tribe of Indians",
    "argMentionid" : "MARKBACKER_20041103.1300-E17-26",
    "start" : 6,
    "end" : 9
  },
  "id" : "MARKBACKER_20041103.1300-R4-1",
  "relationSubType" : "Located",
  "Sentence" : "Arizona does n't use it because one tribe of Indians stretches into three states .",
  "sentence_index" : 18,
  "Tokens" : [ "Arizona", "does", "n't", "use", "it", "because", "one", "tribe", "of", "Indians", "stretches", "into", "three", "states", "." ]
}, {
  "relationType" : "PHYS",
  "extent" : "Of course, they're closer to Japan than to us, and since Japan doesn't use it, Hawaii just plays along",
  "sentence_length" : 25,
  "mentionArg2" : {
    "extent" : "Japan",
    "argMentionid" : "MARKBACKER_20041103.1300-E22-32",
    "start" : 7,
    "end" : 7
  },
  "relationID" : "MARKBACKER_20041103.1300-R5",
  "mentionArg1" : {
    "extent" : "they",
    "argMentionid" : "MARKBACKER_20041103.1300-E21-31",
    "start" : 3,
    "end" : 3
  },
  "id" : "MARKBACKER_20041103.1300-R5-1",
  "relationSubType" : "Near",
  "Sentence" : "Of course , they 're closer to Japan than to us , and since Japan does n't use it , Hawaii just plays along .",
  "sentence_index" : 21,
  "Tokens" : [ "Of", "course", ",", "they", "'re", "closer", "to", "Japan", "than", "to", "us", ",", "and", "since", "Japan", "does", "n't", "use", "it", ",", "Hawaii", "just", "plays", "along", "." ]
}, {
  "relationType" : "PHYS",
  "extent" : "I am tired, hungry, and I leave for work and get home from work in the dark",
  "sentence_length" : 20,
  "mentionArg2" : {
    "extent" : "home",
    "argMentionid" : "MARKBACKER_20041103.1300-E25-57",
    "start" : 13,
    "end" : 13
  },
  "relationID" : "MARKBACKER_20041103.1300-R6",
  "mentionArg1" : {
    "extent" : "I",
    "argMentionid" : "MARKBACKER_20041103.1300-E24-56",
    "start" : 7,
    "end" : 7
  },
  "id" : "MARKBACKER_20041103.1300-R6-1",
  "relationSubType" : "Located",
  "Sentence" : "I am tired , hungry , and I leave for work and get home from work in the dark .",
  "sentence_index" : 29,
  "Tokens" : [ "I", "am", "tired", ",", "hungry", ",", "and", "I", "leave", "for", "work", "and", "get", "home", "from", "work", "in", "the", "dark", "." ]
}, {
  "relationType" : "ART",
  "extent" : "my cube",
  "sentence_length" : 37,
  "mentionArg2" : {
    "extent" : "my cube",
    "argMentionid" : "MARKBACKER_20041103.1300-E28-69",
    "start" : 34,
    "end" : 35
  },
  "relationID" : "MARKBACKER_20041103.1300-R7",
  "mentionArg1" : {
    "extent" : "my",
    "argMentionid" : "MARKBACKER_20041103.1300-E24-68",
    "start" : 34,
    "end" : 34
  },
  "id" : "MARKBACKER_20041103.1300-R7-1",
  "relationSubType" : "User-Owner-Inventor-Manufacturer",
  "Sentence" : "Now , if you 'll excuse me , I have to go stalk the lobby for the girls that are bringing me my Krystals. order and fight to keep myself from falling asleep in my cube .",
  "sentence_index" : 33,
  "Tokens" : [ "Now", ",", "if", "you", "'ll", "excuse", "me", ",", "I", "have", "to", "go", "stalk", "the", "lobby", "for", "the", "girls", "that", "are", "bringing", "me", "my", "Krystals.", "order", "and", "fight", "to", "keep", "myself", "from", "falling", "asleep", "in", "my", "cube", "." ]
}, {
  "relationType" : "PHYS",
  "extent" : "Now, if you'll excuse me, I have to go stalk the lobby for the girls that are bringing me my Krystals",
  "sentence_length" : 37,
  "mentionArg2" : {
    "extent" : "the lobby",
    "argMentionid" : "MARKBACKER_20041103.1300-E26-62",
    "start" : 13,
    "end" : 14
  },
  "relationID" : "MARKBACKER_20041103.1300-R8",
  "mentionArg1" : {
    "extent" : "I",
    "argMentionid" : "MARKBACKER_20041103.1300-E24-61",
    "start" : 8,
    "end" : 8
  },
  "id" : "MARKBACKER_20041103.1300-R8-1",
  "relationSubType" : "Located",
  "Sentence" : "Now , if you 'll excuse me , I have to go stalk the lobby for the girls that are bringing me my Krystals. order and fight to keep myself from falling asleep in my cube .",
  "sentence_index" : 33,
  "Tokens" : [ "Now", ",", "if", "you", "'ll", "excuse", "me", ",", "I", "have", "to", "go", "stalk", "the", "lobby", "for", "the", "girls", "that", "are", "bringing", "me", "my", "Krystals.", "order", "and", "fight", "to", "keep", "myself", "from", "falling", "asleep", "in", "my", "cube", "." ]
}, {
  "relationType" : "PER-SOC",
  "extent" : "Satan's minions",
  "sentence_length" : 22,
  "mentionArg2" : {
    "extent" : "Satan's minions",
    "argMentionid" : "MARKBACKER_20041103.1300-E29-71",
    "start" : 18,
    "end" : 20
  },
  "relationID" : "MARKBACKER_20041103.1300-R9",
  "mentionArg1" : {
    "extent" : "Satan",
    "argMentionid" : "MARKBACKER_20041103.1300-E30-72",
    "start" : 18,
    "end" : 18
  },
  "id" : "MARKBACKER_20041103.1300-R9-1",
  "relationSubType" : "Business",
  "Sentence" : "Amy ???? - ?? - ?? T15:39:00 About time you realized Daylight SavingS time is the work of Satan 's minions .",
  "sentence_index" : 34,
  "Tokens" : [ "Amy", "????", "-", "??", "-", "??", "T15:39:00", "About", "time", "you", "realized", "Daylight", "SavingS", "time", "is", "the", "work", "of", "Satan", "'s", "minions", "." ]
} ]